angdist.py
angdist-1.3.dist-info/LICENSE
angdist-1.3.dist-info/METADATA
angdist-1.3.dist-info/WHEEL
angdist-1.3.dist-info/entry_points.txt
angdist-1.3.dist-info/top_level.txt
angdist-1.3.dist-info/RECORD
