Metadata-Version: 2.1
Name: angdist
Version: 1.3
Summary: Plot the 2D histogram of Euler angles covered by a set of cryo-EM particles
Home-page: https://github.com/Guillawme/angdist
Author: Guillaume Gaullier
Author-email: contact@gaullier.org
License: UNKNOWN
Project-URL: Bug Reports, https://github.com/Guillawme/angdist/issues
Project-URL: Source, https://github.com/Guillawme/angdist
Keywords: cryo-EM Euler angle histogram visualization
Platform: UNKNOWN
Classifier: Development Status :: 5 - Production/Stable
Classifier: Intended Audience :: Science/Research
Classifier: Topic :: Scientific/Engineering
Classifier: Topic :: Scientific/Engineering :: Bio-Informatics
Classifier: Topic :: Scientific/Engineering :: Visualization
Classifier: License :: OSI Approved :: MIT License
Classifier: Programming Language :: Python :: 3
Classifier: Operating System :: OS Independent
Classifier: Environment :: Console
Classifier: Natural Language :: English
Requires-Python: >=3.9.7
License-File: LICENSE
Requires-Dist: click (>=8.0.3)
Requires-Dist: matplotlib (>=3.4.3)
Requires-Dist: starfile (>=0.4.9)
